{
    "/js/admin.js": "/js/admin.js?id=a7fbc76524144eebbb4b",
    "/css/app.css": "/css/app.css?id=0bb49dfd958563367a76",
    "/css/print.css": "/css/print.css?id=8b106b692667777826f6",
    "/css/backend.css": "/css/backend.css?id=0216ba7bc593c94766c1",
    "/js/app.js": "/js/app.js?id=886c738abb1b95ff48cf",
    "/js/coupon.js": "/js/coupon.js?id=c7c67d4209f382477315",
    "/js/mealplans.js": "/js/mealplans.js?id=cf879a5328f2d078fb38",
    "/js/mealpreset.js": "/js/mealpreset.js?id=23e505d3649bc5c855d4",
    "/js/neworder.js": "/js/neworder.js?id=75d35fcaab755c8f5b71",
    "/js/recommendation.js": "/js/recommendation.js?id=bd9442e3ef4756cc4871",
    "/js/report.js": "/js/report.js?id=bfa4b3e650326278687c",
    "/css/plugins.css": "/css/plugins.css?id=38d7e188411f1bdfc73e"
}
